clutch_scraper/__init__.py
clutch_scraper/main.py
clutch_scraper/scraper.py
clutch_scraper-1.2.3.data/scripts/clutch-scraper
clutch_scraper-1.2.3.dist-info/METADATA
clutch_scraper-1.2.3.dist-info/WHEEL
clutch_scraper-1.2.3.dist-info/entry_points.txt
clutch_scraper-1.2.3.dist-info/top_level.txt
clutch_scraper-1.2.3.dist-info/RECORD
