Metadata-Version: 2.4
Name: clutch-scraper
Version: 1.2.3
Summary: A CLI tool to scrape company reviews from Clutch.co
Home-page: https://github.com/dhawalbisht/clutch-scraper
Author: Dhawal Bisht
Author-email: dhawalbisht4543@gmail.com
Classifier: Development Status :: 4 - Beta
Classifier: Intended Audience :: Developers
Classifier: License :: OSI Approved :: MIT License
Classifier: Operating System :: OS Independent
Classifier: Programming Language :: Python :: 3
Classifier: Programming Language :: Python :: 3.7
Classifier: Programming Language :: Python :: 3.8
Classifier: Programming Language :: Python :: 3.9
Classifier: Programming Language :: Python :: 3.10
Classifier: Programming Language :: Python :: 3.11
Requires-Python: >=3.7
Requires-Dist: cloudscraper>=1.2.60
Requires-Dist: beautifulsoup4>=4.11.1
Requires-Dist: pandas>=1.5.0
Requires-Dist: lxml>=4.9.1
Requires-Dist: pymongo
Dynamic: author
Dynamic: author-email
Dynamic: classifier
Dynamic: description
Dynamic: description-content-type
Dynamic: home-page
Dynamic: requires-dist
Dynamic: requires-python
Dynamic: summary
